cnyear/__init__.py
cnyear/cn2dig.py
cnyear/cnyear_obj.py
cnyear/cnyeardb.db
cnyear/cnyeardb_obj.py
cnyear/dig2cn.py
cnyear/tools.py
cnyear/yeargetter.py
cnyear-0.0.12.dist-info/DESCRIPTION.rst
cnyear-0.0.12.dist-info/METADATA
cnyear-0.0.12.dist-info/RECORD
cnyear-0.0.12.dist-info/WHEEL
cnyear-0.0.12.dist-info/metadata.json
cnyear-0.0.12.dist-info/top_level.txt
cnyeardb/__init__.py
cnyeardb/cn2dig.py
cnyeardb/cnyear_obj.py
cnyeardb/cnyeardb.db
cnyeardb/cnyeardb_obj.py
cnyeardb/dig2cn.py
cnyeardb/tools.py
cnyeardb/yeargetter.py
