Metadata-Version: 2.0
Name: cnyear
Version: 0.0.12
Summary: A tool for conversion between Chinese year and CE.
Home-page: https://github.com/nemo-nullius/cnyear
Author: Nemo
Author-email: nonellf@gmail.com
License: GPLv3
Keywords: Chinese regnal year CE conversion
Platform: UNKNOWN
Classifier: Development Status :: 3 - Alpha
Classifier: Intended Audience :: Developers
Classifier: Intended Audience :: Education
Classifier: Intended Audience :: Science/Research
Classifier: License :: OSI Approved :: GNU General Public License v3 (GPLv3)
Classifier: Topic :: Database
Classifier: Programming Language :: Python :: 3.7
